<?xml version="1.0"?><DTS:Executable xmlns:DTS="www.microsoft.com/SqlServer/Dts" DTS:ExecutableType="SSIS.Package.2">
<DTS:Property DTS:Name="PackageFormatVersion">3</DTS:Property>
<DTS:Property DTS:Name="VersionComments"></DTS:Property>
<DTS:Property DTS:Name="CreatorName">AMS\nborio</DTS:Property>
<DTS:Property DTS:Name="CreatorComputerName">AMS06X</DTS:Property>
<DTS:Property DTS:Name="CreationDate" DTS:DataType="7">1/13/2016 2:22:29 PM</DTS:Property>
<DTS:Property DTS:Name="PackageType">5</DTS:Property>
<DTS:Property DTS:Name="ProtectionLevel">1</DTS:Property>
<DTS:Property DTS:Name="MaxConcurrentExecutables">-1</DTS:Property>
<DTS:Property DTS:Name="PackagePriorityClass">0</DTS:Property>
<DTS:Property DTS:Name="VersionMajor">1</DTS:Property>
<DTS:Property DTS:Name="VersionMinor">0</DTS:Property>
<DTS:Property DTS:Name="VersionBuild">160</DTS:Property>
<DTS:Property DTS:Name="VersionGUID">{A53D281F-9D1D-41FB-817B-884C0F3A2473}</DTS:Property>
<DTS:Property DTS:Name="EnableConfig">0</DTS:Property>
<DTS:Property DTS:Name="CheckpointFileName"></DTS:Property>
<DTS:Property DTS:Name="SaveCheckpoints">0</DTS:Property>
<DTS:Property DTS:Name="CheckpointUsage">0</DTS:Property>
<DTS:Property DTS:Name="SuppressConfigurationWarnings">0</DTS:Property>
<DTS:ConnectionManager>
<DTS:Property DTS:Name="DelayValidation">0</DTS:Property>
<DTS:Property DTS:Name="ObjectName">AMS06X.DW_SALUD</DTS:Property>
<DTS:Property DTS:Name="DTSID">{020DAF9F-837C-42F1-9C2F-54AC3945F831}</DTS:Property>
<DTS:Property DTS:Name="Description"></DTS:Property>
<DTS:Property DTS:Name="CreationName">OLEDB</DTS:Property><DTS:ObjectData><DTS:ConnectionManager>
<DTS:Property DTS:Name="Retain">0</DTS:Property>
<DTS:Property DTS:Name="ConnectionString">Data Source=AMS06X;Initial Catalog=DW_SALUD;Provider=SQLNCLI10.1;Integrated Security=SSPI;Application Name=SSIS-Padron_R650-{020DAF9F-837C-42F1-9C2F-54AC3945F831}AMS06X.DW_SALUD;Auto Translate=False;</DTS:Property></DTS:ConnectionManager></DTS:ObjectData></DTS:ConnectionManager>
<DTS:ConnectionManager>
<DTS:Property DTS:Name="DelayValidation">0</DTS:Property>
<DTS:Property DTS:Name="ObjectName">AMS06X.msdb</DTS:Property>
<DTS:Property DTS:Name="DTSID">{2EECFFC1-6466-48B4-AD0E-5C9070FF8DEA}</DTS:Property>
<DTS:Property DTS:Name="Description"></DTS:Property>
<DTS:Property DTS:Name="CreationName">OLEDB</DTS:Property><DTS:ObjectData><DTS:ConnectionManager>
<DTS:Property DTS:Name="Retain">0</DTS:Property>
<DTS:Property DTS:Name="ConnectionString">Data Source=AMS06X;Initial Catalog=msdb;Provider=SQLNCLI10.1;Integrated Security=SSPI;Application Name=SSIS-Padron_R650-{2EECFFC1-6466-48B4-AD0E-5C9070FF8DEA}AMS06X.msdb;Auto Translate=False;</DTS:Property></DTS:ConnectionManager></DTS:ObjectData></DTS:ConnectionManager>
<DTS:LogProvider>
<DTS:Property DTS:Name="ConfigString">AMS06X.msdb</DTS:Property>
<DTS:Property DTS:Name="DelayValidation">0</DTS:Property>
<DTS:Property DTS:Name="ObjectName">SSIS log provider for SQL Server</DTS:Property>
<DTS:Property DTS:Name="DTSID">{743F8C0F-06C7-4933-B59B-1B691D2E0AB9}</DTS:Property>
<DTS:Property DTS:Name="Description">Writes log entries for events to a SQL Server database</DTS:Property>
<DTS:Property DTS:Name="CreationName">DTS.LogProviderSQLServer.2</DTS:Property><DTS:ObjectData><InnerObject/></DTS:ObjectData></DTS:LogProvider>
<DTS:Property DTS:Name="LastModifiedProductVersion">10.50.1600.1</DTS:Property>
<DTS:Property DTS:Name="ForceExecValue">0</DTS:Property>
<DTS:Property DTS:Name="ExecValue" DTS:DataType="3">0</DTS:Property>
<DTS:Property DTS:Name="ForceExecutionResult">-1</DTS:Property>
<DTS:Property DTS:Name="Disabled">0</DTS:Property>
<DTS:Property DTS:Name="FailPackageOnFailure">0</DTS:Property>
<DTS:Property DTS:Name="FailParentOnFailure">0</DTS:Property>
<DTS:Property DTS:Name="MaxErrorCount">1</DTS:Property>
<DTS:Property DTS:Name="ISOLevel">1048576</DTS:Property>
<DTS:Property DTS:Name="LocaleID">11274</DTS:Property>
<DTS:Property DTS:Name="TransactionOption">1</DTS:Property>
<DTS:Property DTS:Name="DelayValidation">-1</DTS:Property>
<DTS:LoggingOptions>
<DTS:Property DTS:Name="LoggingMode">1</DTS:Property>
<DTS:Property DTS:Name="FilterKind">0</DTS:Property>
<DTS:Property DTS:Name="EventFilter" DTS:DataType="8">1,7,OnError</DTS:Property>
<DTS:Property DTS:Name="ColumnFilter" DTS:EventName="OnError">
<DTS:Property DTS:Name="Computer">-1</DTS:Property>
<DTS:Property DTS:Name="Operator">-1</DTS:Property>
<DTS:Property DTS:Name="SourceName">-1</DTS:Property>
<DTS:Property DTS:Name="SourceID">-1</DTS:Property>
<DTS:Property DTS:Name="ExecutionID">-1</DTS:Property>
<DTS:Property DTS:Name="MessageText">-1</DTS:Property>
<DTS:Property DTS:Name="DataBytes">-1</DTS:Property></DTS:Property><DTS:SelectedLogProvider DTS:InstanceID="{743F8C0F-06C7-4933-B59B-1B691D2E0AB9}"/></DTS:LoggingOptions>
<DTS:Executable DTS:ExecutableType="Microsoft.SqlServer.Dts.Tasks.ExecuteSQLTask.ExecuteSQLTask, Microsoft.SqlServer.SQLTask, Version=10.0.0.0, Culture=neutral, PublicKeyToken=89845dcd8080cc91" DTS:ThreadHint="0">
<DTS:Property DTS:Name="ExecutionLocation">0</DTS:Property>
<DTS:Property DTS:Name="ExecutionAddress"></DTS:Property>
<DTS:Property DTS:Name="TaskContact">Execute SQL Task; Microsoft Corporation; Microsoft SQL Server 2008 R2; © 2007 Microsoft Corporation; All Rights Reserved;http://www.microsoft.com/sql/support/default.asp;1</DTS:Property>
<DTS:Property DTS:Name="ForceExecValue">0</DTS:Property>
<DTS:Property DTS:Name="ExecValue" DTS:DataType="3">0</DTS:Property>
<DTS:Property DTS:Name="ForceExecutionResult">-1</DTS:Property>
<DTS:Property DTS:Name="Disabled">0</DTS:Property>
<DTS:Property DTS:Name="FailPackageOnFailure">0</DTS:Property>
<DTS:Property DTS:Name="FailParentOnFailure">0</DTS:Property>
<DTS:Property DTS:Name="MaxErrorCount">1</DTS:Property>
<DTS:Property DTS:Name="ISOLevel">1048576</DTS:Property>
<DTS:Property DTS:Name="LocaleID">-1</DTS:Property>
<DTS:Property DTS:Name="TransactionOption">1</DTS:Property>
<DTS:Property DTS:Name="DelayValidation">0</DTS:Property>
<DTS:LoggingOptions>
<DTS:Property DTS:Name="LoggingMode">0</DTS:Property>
<DTS:Property DTS:Name="FilterKind">0</DTS:Property>
<DTS:Property DTS:Name="EventFilter" DTS:DataType="8"></DTS:Property></DTS:LoggingOptions>
<DTS:Property DTS:Name="ObjectName">Formulario 60 y 90</DTS:Property>
<DTS:Property DTS:Name="DTSID">{4cc10ca0-59b0-421c-91ee-bec8ede70abd}</DTS:Property>
<DTS:Property DTS:Name="Description">Execute SQL Task</DTS:Property>
<DTS:Property DTS:Name="CreationName">Microsoft.SqlServer.Dts.Tasks.ExecuteSQLTask.ExecuteSQLTask, Microsoft.SqlServer.SQLTask, Version=10.0.0.0, Culture=neutral, PublicKeyToken=89845dcd8080cc91</DTS:Property>
<DTS:Property DTS:Name="DisableEventHandlers">0</DTS:Property><DTS:ObjectData><SQLTask:SqlTaskData SQLTask:Connection="{020DAF9F-837C-42F1-9C2F-54AC3945F831}" SQLTask:TimeOut="0" SQLTask:IsStoredProc="False" SQLTask:BypassPrepare="True" SQLTask:SqlStmtSourceType="DirectInput" SQLTask:SqlStatementSource="&#xA;SET DATEFORMAT 'YMD'&#xA;&#xA;	DELETE dbo.AUX_H_R650_FORMULARIO_60y90&#xA;	&#xA;&#xA;-- Encuentra el Periodo Actual de consumos.&#xA;	DECLARE @Ult_Periodo_Consumo CHAR(6) SET @Ult_Periodo_Consumo = (SELECT MAX(id_periodo) from D_PERIODO where vigente_consumo = 1)&#xA;&#xA;-- Encuentra el Periodo perteneciente a 10 meses anteriores al Periodo Actual. Esto es para no asegurarse de &#xA;	DECLARE @Periodo_Minimo int SET @Periodo_Minimo = (SELECT dbo.Periodo8MesesAtras(@Ult_Periodo_Consumo))&#xA;&#xA;&#xA;			select a11.Id_Tipo_Beneficiario, a14.id_provincia, a11.id_periodo, a11.Id_Padron, a12.id_cod_resolucion, sum(a11.cant_prest_int_acep)  WJXBFS1, 15 as id_entidad_capita, 0 as id_trimestre, SUBSTRING(CAST(a11.id_periodo as CHAR(6)),1,4) as id_anio&#xA;			into #ZZTGQOTURONSP000&#xA;			from H_ORD_INT_DET a11&#xA;			 join D_PRESTACION a12 on  (a11.id_prestacion = a12.id_prestacion)&#xA;			 join D_PERSONAS a13 on  (a11.id_persona = a13.id_persona)&#xA;			 join D_LOCALIDADES_AFILIADO a14 on  (a13.id_localidad_afiliado = a14.id_localidad_afiliado)&#xA;			 join D_TIPOS_BENEFICIARIOS a15 on  (a11.Id_Tipo_Beneficiario = a15.Id_Tipo_Beneficiario)&#xA;			 join D_PRODUCTOS a16 on  (a11.id_producto = a16.id_producto)&#xA;			where a11.id_periodo &gt; @Periodo_Minimo AND a11.id_periodo &lt;= @Ult_Periodo_Consumo&#xA;			 and a15.Id_Grupo_Tipo_Beneficiario in (1, 2)&#xA;			 and NOT EXISTS (SELECT * FROM FILTRO_PLAN_PRODUCTO a17 WHERE a11.id_producto_original=a17.id_producto and a11.id_plan_producto_original=a17.id_plan_producto)&#xA;			 and a12.id_cod_resolucion in ('B', 'C', 'D', 'E', 'F', 'G', 'A')&#xA;			 and a11.id_origen_prestacion in ('A')&#xA;			group by a11.Id_Tipo_Beneficiario, a14.id_provincia, a11.id_periodo, a11.Id_Padron, a12.id_cod_resolucion &#xA;&#xA;			select a11.Id_Tipo_Beneficiario, a14.id_provincia, a11.id_periodo, a11.Id_Padron, a12.id_cod_resolucion, sum(a11.cant_prest_amb_acep)  WJXBFS1, 15 as id_entidad_capita, 0 as id_trimestre, SUBSTRING(CAST(a11.id_periodo as CHAR(6)),1,4) as id_anio&#xA;			into #ZZTXYS9U82FSP001&#xA;			from H_ORD_AMB_DET a11&#xA;			 join D_PRESTACION a12 on  (a11.id_prestacion = a12.id_prestacion)&#xA;			 join D_PERSONAS a13 on  (a11.id_persona = a13.id_persona)&#xA;			 join D_LOCALIDADES_AFILIADO a14 on  (a13.id_localidad_afiliado = a14.id_localidad_afiliado)&#xA;			 join D_TIPOS_BENEFICIARIOS a15  on  (a11.Id_Tipo_Beneficiario = a15.Id_Tipo_Beneficiario)&#xA;			 join D_PRODUCTOS a16 on  (a11.id_producto = a16.id_producto)&#xA;			where a11.id_periodo &gt; @Periodo_Minimo AND a11.id_periodo &lt;= @Ult_Periodo_Consumo&#xA;			 and a15.Id_Grupo_Tipo_Beneficiario in (1, 2)&#xA;			 and NOT EXISTS (SELECT * FROM FILTRO_PLAN_PRODUCTO a17 WHERE a11.id_producto_original=a17.id_producto and a11.id_plan_producto_original=a17.id_plan_producto)&#xA;			 and a12.id_cod_resolucion in ('B', 'C', 'D', 'E', 'F', 'G', 'A')&#xA;			 and a11.id_origen_prestacion in ('A')&#xA;			group by a11.Id_Tipo_Beneficiario, a14.id_provincia, a11.id_periodo, a11.Id_Padron, a12.id_cod_resolucion &#xA;&#xA;&#xA;			INSERT INTO dbo.AUX_H_R650_FORMULARIO_60y90&#xA;			(ID_Periodo,&#xA;			 id_provincia,&#xA;			 id_padron,&#xA;			 Id_Grupo_Tipo_Beneficiario,&#xA;			 id_cod_resolucion,&#xA;			 cantidad_60y90,&#xA;			 id_entidad_capita)&#xA;			select distinct &#xA;			coalesce(pa11.ID_Periodo, pa12.ID_Periodo)  ID_Periodo,&#xA;			coalesce(pa11.id_provincia, pa12.id_provincia)  id_provincia,&#xA;			coalesce(pa11.Id_Padron, pa12.Id_Padron)  Id_Padron,&#xA;			a13.Id_Grupo_Tipo_Beneficiario  Id_Grupo_Tipo_Beneficiario, &#xA;			coalesce(pa11.id_cod_resolucion, pa12.id_cod_resolucion)  id_cod_resolucion,&#xA;			(ISNULL(pa11.WJXBFS1, 0) + ISNULL(pa12.WJXBFS1, 0))  cantidad_60y90,&#xA;			pa12.id_entidad_capita&#xA;			from #ZZTGQOTURONSP000 pa11&#xA;			 full outer join #ZZTXYS9U82FSP001 pa12&#xA;			   on  (pa11.ID_Periodo = pa12.ID_Periodo and &#xA;				pa11.Id_Padron = pa12.Id_Padron and &#xA;				pa11.id_cod_resolucion = pa12.id_cod_resolucion and &#xA;				pa11.id_provincia = pa12.id_provincia)&#xA;			 join D_TIPOS_BENEFICIARIOS a13 on  (coalesce(pa11.Id_Tipo_Beneficiario, pa12.Id_Tipo_Beneficiario) = a13.Id_Tipo_Beneficiario)&#xA;			 join D_CODIGOS_RESOLUCION650 a14 on  (coalesce(pa11.id_cod_resolucion, pa12.id_cod_resolucion) = a14.id_cod_resolucion)&#xA;			 join D_PADRON_AFILIADOS a15 on  (coalesce(pa11.Id_Padron, pa12.Id_Padron) = a15.Id_Padron)&#xA;			 join D_PROVINCIA a16 on  (coalesce(pa11.id_provincia, pa12.id_provincia) = a16.id_provincia)&#xA;			 join D_GRUPO_TIPOS_BENEFICIARIO a17 on  (a13.Id_Grupo_Tipo_Beneficiario = a17.Id_Grupo_Tipo_Beneficiario)&#xA;			ORDER BY id_provincia, id_cod_resolucion, Id_Padron, Id_Grupo_Tipo_Beneficiario&#xA;&#xA;			drop table #ZZTGQOTURONSP000&#xA;			drop table #ZZTXYS9U82FSP001&#xA;&#xA;	UPDATE AUX_H_R650_FORMULARIO_60y90 	SET id_anio = P.id_anio, id_trimestre_r650 = P.id_trimestre&#xA;	FROM AUX_H_R650_FORMULARIO_60y90 R JOIN D_PERIODO P on R.id_periodo = P.id_periodo&#xA;	where id_entidad_capita = 15 and R.id_trimestre_r650 is null&#xA;			&#xA;	 --Borra periodo ya existente.&#xA;	 DELETE DW_SALUD.dbo.H_R650_FORMULARIO_60y90&#xA;	 FROM DW_SALUD.dbo.H_R650_FORMULARIO_60y90 A&#xA;	 JOIN dbo.AUX_H_R650_FORMULARIO_60y90 H on H.id_trimestre_r650 = A.id_trimestre_r650 AND H.id_anio = A.id_anio AND H.id_entidad_capita = A.id_entidad_capita AND H.id_periodo = A.id_periodo &#xA;&#xA;	INSERT INTO H_R650_FORMULARIO_60y90&#xA;	SELECT id_periodo, id_provincia, Id_padron, Id_Grupo_Tipo_Beneficiario, id_cod_resolucion, cantidad_60y90, id_trimestre_r650, id_anio, id_entidad_capita&#xA;	FROM dbo.AUX_H_R650_FORMULARIO_60y90&#xA;	WHERE cantidad_60y90 &lt;&gt; 0&#xA;	&#xA;&#xA;	DELETE dbo.AUX_H_R650_FORMULARIO_60y90&#xA;	&#xA;	&#xA;" SQLTask:CodePage="1252" SQLTask:ResultType="ResultSetType_None" xmlns:SQLTask="www.microsoft.com/sqlserver/dts/tasks/sqltask"/></DTS:ObjectData></DTS:Executable>
<DTS:Executable DTS:ExecutableType="Microsoft.SqlServer.Dts.Tasks.ExecuteSQLTask.ExecuteSQLTask, Microsoft.SqlServer.SQLTask, Version=10.0.0.0, Culture=neutral, PublicKeyToken=89845dcd8080cc91" DTS:ThreadHint="0">
<DTS:Property DTS:Name="ExecutionLocation">0</DTS:Property>
<DTS:Property DTS:Name="ExecutionAddress"></DTS:Property>
<DTS:Property DTS:Name="TaskContact">Execute SQL Task; Microsoft Corporation; Microsoft SQL Server 2008 R2; © 2007 Microsoft Corporation; All Rights Reserved;http://www.microsoft.com/sql/support/default.asp;1</DTS:Property>
<DTS:Property DTS:Name="ForceExecValue">0</DTS:Property>
<DTS:Property DTS:Name="ExecValue" DTS:DataType="3">0</DTS:Property>
<DTS:Property DTS:Name="ForceExecutionResult">-1</DTS:Property>
<DTS:Property DTS:Name="Disabled">0</DTS:Property>
<DTS:Property DTS:Name="FailPackageOnFailure">0</DTS:Property>
<DTS:Property DTS:Name="FailParentOnFailure">0</DTS:Property>
<DTS:Property DTS:Name="MaxErrorCount">1</DTS:Property>
<DTS:Property DTS:Name="ISOLevel">1048576</DTS:Property>
<DTS:Property DTS:Name="LocaleID">-1</DTS:Property>
<DTS:Property DTS:Name="TransactionOption">1</DTS:Property>
<DTS:Property DTS:Name="DelayValidation">0</DTS:Property>
<DTS:LoggingOptions>
<DTS:Property DTS:Name="LoggingMode">0</DTS:Property>
<DTS:Property DTS:Name="FilterKind">0</DTS:Property>
<DTS:Property DTS:Name="EventFilter" DTS:DataType="8"></DTS:Property></DTS:LoggingOptions>
<DTS:Property DTS:Name="ObjectName">Formulario 70</DTS:Property>
<DTS:Property DTS:Name="DTSID">{3523c1d7-3aad-445b-a10d-3ca975eefe09}</DTS:Property>
<DTS:Property DTS:Name="Description">Execute SQL Task</DTS:Property>
<DTS:Property DTS:Name="CreationName">Microsoft.SqlServer.Dts.Tasks.ExecuteSQLTask.ExecuteSQLTask, Microsoft.SqlServer.SQLTask, Version=10.0.0.0, Culture=neutral, PublicKeyToken=89845dcd8080cc91</DTS:Property>
<DTS:Property DTS:Name="DisableEventHandlers">0</DTS:Property><DTS:ObjectData><SQLTask:SqlTaskData SQLTask:Connection="{020DAF9F-837C-42F1-9C2F-54AC3945F831}" SQLTask:TimeOut="0" SQLTask:IsStoredProc="False" SQLTask:BypassPrepare="True" SQLTask:SqlStmtSourceType="DirectInput" SQLTask:SqlStatementSource="&#xA;SET DATEFORMAT 'YMD'&#xA;&#xA;	DELETE FROM dbo.AUX_H_R650_FORMULARIO_70&#xA;&#xA;-- Encuentra el Periodo Actual de consumos.&#xA;	DECLARE @Ult_Periodo_Consumo CHAR(6) SET @Ult_Periodo_Consumo = (SELECT MAX(id_periodo) from D_PERIODO where vigente_consumo = 1)&#xA;&#xA;-- Encuentra el Periodo perteneciente a 10 meses anteriores al Periodo Actual. Esto es para no asegurarse de &#xA;	DECLARE @Periodo_Minimo int SET @Periodo_Minimo = (SELECT dbo.Periodo8MesesAtras(@Ult_Periodo_Consumo))&#xA;&#xA;&#xA;	INSERT INTO dbo.AUX_H_R650_FORMULARIO_70&#xA;	(id_periodo, id_provincia, Id_Grupo_Tipo_Beneficiario, id_tipo_internacion, Id_Padron, cant_dias, cant_egresos, id_anio, id_entidad_capita)&#xA;	select a11.id_periodo, a18.id_provincia, a12.Id_Grupo_Tipo_Beneficiario, a11.id_tipo_internacion, a11.Id_Padron, sum(a11.dias_aut_int)  cant_dias, sum(a11.cant_internaciones) cant_egresos, SUBSTRING(CAST(a11.id_periodo as CHAR(6)),1,4) as id_anio, 15 as id_entidad_capita&#xA;	from H_INTERNACIONES a11&#xA;	 join D_TIPOS_BENEFICIARIOS a12 on (a11.Id_Tipo_Beneficiario = a12.Id_Tipo_Beneficiario)&#xA;	 join D_PERSONAS a13 on  (a11.id_persona = a13.id_persona)&#xA;	 join D_LOCALIDADES_AFILIADO a14  on  (a13.id_localidad_afiliado = a14.id_localidad_afiliado)&#xA;	 join D_PRODUCTOS a15  on  (a11.id_producto = a15.id_producto)&#xA;	 join D_GRUPO_TIPOS_BENEFICIARIO a16 on  (a12.Id_Grupo_Tipo_Beneficiario = a16.Id_Grupo_Tipo_Beneficiario)&#xA;	 join D_PADRON_AFILIADOS a17 on  (a11.Id_Padron = a17.Id_Padron)	 &#xA;	 join D_PROVINCIA a18  on  (a14.id_provincia = a18.id_provincia)&#xA;	 join D_TIPO_INTERNACION a19 on  (a11.id_tipo_internacion = a19.id_tipo_internacion)&#xA;	where (a11.id_periodo &gt; @Periodo_Minimo AND a11.id_periodo &lt;= @Ult_Periodo_Consumo&#xA;	and NOT EXISTS (SELECT * FROM FILTRO_PLAN_PRODUCTO a20 WHERE a11.id_producto = a20.id_producto and a11.id_plan_producto = a20.id_plan_producto)&#xA;	 and a12.Id_Grupo_Tipo_Beneficiario in (1, 2)&#xA;	 and a11.id_estado_aut_orden in (3, 4)&#xA;	 and a15.id_segmento not in (3)&#xA;	 and a11.id_tipo_internacion not in ('CD', 'CP'))&#xA;	group by a18.id_provincia, a11.Id_Padron, a12.Id_Grupo_Tipo_Beneficiario, a11.id_periodo, a11.id_tipo_internacion&#xA;	 &#xA;	UPDATE AUX_H_R650_FORMULARIO_70	SET id_trimestre_r650 = P.id_trimestre&#xA;	FROM AUX_H_R650_FORMULARIO_70 R JOIN D_PERIODO P on R.id_periodo = P.id_periodo&#xA;	where id_entidad_capita = 15 and R.id_trimestre_r650 is null&#xA;	 &#xA;	-- Borra periodo ya existente.&#xA;	 DELETE DW_SALUD.dbo.H_R650_FORMULARIO_70&#xA;	 FROM DW_SALUD.dbo.H_R650_FORMULARIO_70 A&#xA;	 JOIN dbo.AUX_H_R650_FORMULARIO_70 H on H.id_trimestre_r650 = A.id_trimestre_r650 AND H.id_anio = A.id_anio AND H.id_entidad_capita = A.id_entidad_capita AND H.id_periodo = A.id_periodo &#xA;&#xA;	INSERT INTO H_R650_FORMULARIO_70&#xA;	(id_periodo, id_provincia, Id_Grupo_Tipo_Beneficiario, Id_Tipo_Internacion, Id_padron, Cant_dias, Cant_egresos, id_trimestre_r650, id_anio, id_entidad_capita)&#xA;	SELECT id_periodo, id_provincia, Id_Grupo_Tipo_Beneficiario, Id_Tipo_Internacion, Id_padron, Cant_dias, Cant_egresos, id_trimestre_r650, id_anio, id_entidad_capita&#xA;	FROM dbo.AUX_H_R650_FORMULARIO_70&#xA;	&#xA;	DELETE dbo.AUX_H_R650_FORMULARIO_70&#xA;	" SQLTask:CodePage="1252" SQLTask:ResultType="ResultSetType_None" xmlns:SQLTask="www.microsoft.com/sqlserver/dts/tasks/sqltask"/></DTS:ObjectData></DTS:Executable>
<DTS:Executable DTS:ExecutableType="Microsoft.SqlServer.Dts.Tasks.ExecuteSQLTask.ExecuteSQLTask, Microsoft.SqlServer.SQLTask, Version=10.0.0.0, Culture=neutral, PublicKeyToken=89845dcd8080cc91" DTS:ThreadHint="0">
<DTS:Property DTS:Name="ExecutionLocation">0</DTS:Property>
<DTS:Property DTS:Name="ExecutionAddress"></DTS:Property>
<DTS:Property DTS:Name="TaskContact">Execute SQL Task; Microsoft Corporation; Microsoft SQL Server 2008 R2; © 2007 Microsoft Corporation; All Rights Reserved;http://www.microsoft.com/sql/support/default.asp;1</DTS:Property>
<DTS:Property DTS:Name="ForceExecValue">0</DTS:Property>
<DTS:Property DTS:Name="ExecValue" DTS:DataType="3">0</DTS:Property>
<DTS:Property DTS:Name="ForceExecutionResult">-1</DTS:Property>
<DTS:Property DTS:Name="Disabled">0</DTS:Property>
<DTS:Property DTS:Name="FailPackageOnFailure">0</DTS:Property>
<DTS:Property DTS:Name="FailParentOnFailure">0</DTS:Property>
<DTS:Property DTS:Name="MaxErrorCount">1</DTS:Property>
<DTS:Property DTS:Name="ISOLevel">1048576</DTS:Property>
<DTS:Property DTS:Name="LocaleID">-1</DTS:Property>
<DTS:Property DTS:Name="TransactionOption">1</DTS:Property>
<DTS:Property DTS:Name="DelayValidation">0</DTS:Property>
<DTS:LoggingOptions>
<DTS:Property DTS:Name="LoggingMode">0</DTS:Property>
<DTS:Property DTS:Name="FilterKind">0</DTS:Property>
<DTS:Property DTS:Name="EventFilter" DTS:DataType="8"></DTS:Property></DTS:LoggingOptions>
<DTS:Property DTS:Name="ObjectName">Formulario 80 AMB</DTS:Property>
<DTS:Property DTS:Name="DTSID">{370cbab0-f37c-482d-a8ac-c5f180c0b32e}</DTS:Property>
<DTS:Property DTS:Name="Description">Execute SQL Task</DTS:Property>
<DTS:Property DTS:Name="CreationName">Microsoft.SqlServer.Dts.Tasks.ExecuteSQLTask.ExecuteSQLTask, Microsoft.SqlServer.SQLTask, Version=10.0.0.0, Culture=neutral, PublicKeyToken=89845dcd8080cc91</DTS:Property>
<DTS:Property DTS:Name="DisableEventHandlers">0</DTS:Property><DTS:ObjectData><SQLTask:SqlTaskData SQLTask:Connection="{020DAF9F-837C-42F1-9C2F-54AC3945F831}" SQLTask:TimeOut="0" SQLTask:IsStoredProc="False" SQLTask:BypassPrepare="True" SQLTask:SqlStmtSourceType="DirectInput" SQLTask:SqlStatementSource="&#xA;SET DATEFORMAT 'YMD'&#xA;&#xA;	DELETE FROM dbo.AUX_H_R650_FORMULARIO_80_AMB&#xA;&#xA;-- Encuentra el Periodo Actual de consumos.&#xA;	DECLARE @Ult_Periodo_Consumo CHAR(6) SET @Ult_Periodo_Consumo = (SELECT MAX(id_periodo) from D_PERIODO where vigente_consumo = 1)&#xA;&#xA;-- Encuentra el Periodo perteneciente a 10 meses anteriores al Periodo Actual. Esto es para no asegurarse de &#xA;	DECLARE @Periodo_Minimo int SET @Periodo_Minimo = (SELECT dbo.Periodo8MesesAtras(@Ult_Periodo_Consumo))&#xA;&#xA;&#xA;			select a11.Id_Tipo_Beneficiario, a16.id_provincia, a11.id_periodo, a11.Id_Padron, a11.id_origen_prestacion, a12.id_cod_resolucion, count(distinct a11.id_persona)  WJXBFS1, 15 as id_entidad_capita, SUBSTRING(CAST(a11.id_periodo as CHAR(6)),1,4) as id_anio&#xA;			into #ZZTXMEHN17PSP000&#xA;			from H_ORD_AMB_DET a11&#xA;			 join D_PRESTACION a12  on  (a11.id_prestacion = a12.id_prestacion)&#xA;			 join D_TIPOS_BENEFICIARIOS a13  on  (a11.Id_Tipo_Beneficiario = a13.Id_Tipo_Beneficiario)&#xA;			 join D_PRODUCTOS a14  on  (a11.id_producto = a14.id_producto)&#xA;			 join D_PERSONAS a15   on  (a11.id_persona = a15.id_persona)&#xA;			 join D_LOCALIDADES_AFILIADO a16   on  (a15.id_localidad_afiliado = a16.id_localidad_afiliado)&#xA;			where (a11.id_periodo &gt; @Periodo_Minimo AND a11.id_periodo &lt;= @Ult_Periodo_Consumo&#xA;			 and a13.Id_Grupo_Tipo_Beneficiario in (1, 2)&#xA;			and NOT EXISTS (SELECT * FROM FILTRO_PLAN_PRODUCTO a20 WHERE a11.id_producto=a20.id_producto and a11.id_plan_producto=a20.id_plan_producto)&#xA;			 and a12.id_cod_resolucion in ('J', 'K', 'L', 'M')&#xA;			 and a11.id_origen_prestacion in ('A'))&#xA;			group by a11.Id_Tipo_Beneficiario, a16.id_provincia, a11.id_periodo, a11.Id_Padron, a11.id_origen_prestacion, a12.id_cod_resolucion &#xA;&#xA;			select a11.Id_Tipo_Beneficiario, a16.id_provincia, a11.id_periodo, a11.Id_Padron, a11.id_origen_prestacion, a12.id_cod_resolucion, count(distinct a11.id_persona)  WJXBFS1, 15 as id_entidad_capita, SUBSTRING(CAST(a11.id_periodo as CHAR(6)),1,4) as id_anio&#xA;			into #ZZTHPYUM939SP001&#xA;			from H_ORD_INT_DET a11&#xA;			 join D_PRESTACION a12  on  (a11.id_prestacion = a12.id_prestacion)&#xA;			 join D_TIPOS_BENEFICIARIOS a13   on  (a11.Id_Tipo_Beneficiario = a13.Id_Tipo_Beneficiario)&#xA;			 join D_PRODUCTOS a14  on  (a11.id_producto = a14.id_producto)&#xA;			 join D_PERSONAS a15  on  (a11.id_persona = a15.id_persona)&#xA;			 join D_LOCALIDADES_AFILIADO a16   on  (a15.id_localidad_afiliado = a16.id_localidad_afiliado)&#xA;			where (a11.id_periodo &gt; @Periodo_Minimo AND a11.id_periodo &lt;= @Ult_Periodo_Consumo&#xA;			 and a13.Id_Grupo_Tipo_Beneficiario in (1, 2)&#xA;			 and NOT EXISTS (SELECT * FROM FILTRO_PLAN_PRODUCTO a20 WHERE a11.id_producto=a20.id_producto and a11.id_plan_producto=a20.id_plan_producto)&#xA;			 and a12.id_cod_resolucion in ('J', 'K', 'L', 'M')&#xA;			 and a11.id_origen_prestacion in ('A'))&#xA;			group by a11.Id_Tipo_Beneficiario, a16.id_provincia, a11.id_periodo, a11.Id_Padron, a11.id_origen_prestacion, a12.id_cod_resolucion &#xA;&#xA;			INSERT INTO dbo.AUX_H_R650_FORMULARIO_80_AMB&#xA;			(ID_Periodo,&#xA;			 id_provincia,&#xA;			 id_padron,&#xA;			 Id_Grupo_Tipo_Beneficiario,&#xA;			 id_cod_resolucion,&#xA;			 cantidad_80A,&#xA;			 id_entidad_capita)&#xA;			select distinct &#xA;			 coalesce(pa11.ID_Periodo, pa12.ID_Periodo)  ID_Periodo,&#xA;			 coalesce(pa11.id_provincia, pa12.id_provincia)  id_provincia,&#xA;			 coalesce(pa11.Id_Padron, pa12.Id_Padron)  Id_Padron,&#xA;			 a13.Id_Grupo_Tipo_Beneficiario  Id_Grupo_Tipo_Beneficiario,&#xA;			 coalesce(pa11.id_cod_resolucion, pa12.id_cod_resolucion)  id_cod_resolucion,&#xA;			 ROUND(ISNULL(((ISNULL(pa11.WJXBFS1, 0) + ISNULL(pa12.WJXBFS1, 0)) / 2.0), 0), 0)  cantidad_80A,&#xA;			 Pa11.id_entidad_capita&#xA;			 from #ZZTXMEHN17PSP000 pa11&#xA;			 full outer join #ZZTHPYUM939SP001 pa12&#xA;			   on  (pa11.ID_Periodo = pa12.ID_Periodo and &#xA;			 pa11.Id_Padron = pa12.Id_Padron and &#xA;			 pa11.Id_Tipo_Beneficiario = pa12.Id_Tipo_Beneficiario and &#xA;			 pa11.id_cod_resolucion = pa12.id_cod_resolucion and &#xA;			 pa11.id_origen_prestacion = pa12.id_origen_prestacion and &#xA;			 pa11.id_provincia = pa12.id_provincia)&#xA;			 join D_TIPOS_BENEFICIARIOS a13  on  (coalesce(pa11.Id_Tipo_Beneficiario, pa12.Id_Tipo_Beneficiario) = a13.Id_Tipo_Beneficiario)&#xA;			 join D_CODIGOS_RESOLUCION650 a14   on  (coalesce(pa11.id_cod_resolucion, pa12.id_cod_resolucion) = a14.id_cod_resolucion)&#xA;			 join D_ORIGEN_PRESTACION a15  on  (coalesce(pa11.id_origen_prestacion, pa12.id_origen_prestacion) = a15.id_origen_prestacion)&#xA;			 join D_PADRON_AFILIADOS a16  on  (coalesce(pa11.Id_Padron, pa12.Id_Padron) = a16.Id_Padron)&#xA;			 join D_PROVINCIA a17  on  (coalesce(pa11.id_provincia, pa12.id_provincia) = a17.id_provincia)&#xA;			 join D_GRUPO_TIPOS_BENEFICIARIO a18  on  (a13.Id_Grupo_Tipo_Beneficiario = a18.Id_Grupo_Tipo_Beneficiario)&#xA;&#xA;			drop table #ZZTXMEHN17PSP000&#xA;			drop table #ZZTHPYUM939SP001&#xA;&#xA;&#xA;	UPDATE AUX_H_R650_FORMULARIO_80_AMB	SET id_anio = P.id_anio, id_trimestre_r650 = P.id_trimestre&#xA;	FROM AUX_H_R650_FORMULARIO_80_AMB R JOIN D_PERIODO P on R.id_periodo = P.id_periodo&#xA;	where id_entidad_capita = 15 and R.id_trimestre_r650 is null&#xA;			&#xA;	 --Borra periodo ya existente.&#xA;	 DELETE DW_SALUD.dbo.H_R650_FORMULARIO_80_AMB&#xA;	 FROM DW_SALUD.dbo.H_R650_FORMULARIO_80_AMB A&#xA;	 JOIN dbo.AUX_H_R650_FORMULARIO_80_AMB H on H.id_trimestre_r650 = A.id_trimestre_r650 AND H.id_anio = A.id_anio AND H.id_entidad_capita = A.id_entidad_capita AND H.id_periodo = A.id_periodo &#xA;&#xA;	INSERT INTO H_R650_FORMULARIO_80_AMB&#xA;	SELECT id_periodo, id_provincia, Id_padron, Id_Grupo_Tipo_Beneficiario, id_cod_resolucion, cantidad_80A, id_trimestre_r650, id_anio, id_entidad_capita&#xA;	FROM dbo.AUX_H_R650_FORMULARIO_80_AMB&#xA;		&#xA;	DELETE dbo.AUX_H_R650_FORMULARIO_80_AMB&#xA;&#xA;		" SQLTask:CodePage="1252" SQLTask:ResultType="ResultSetType_None" xmlns:SQLTask="www.microsoft.com/sqlserver/dts/tasks/sqltask"/></DTS:ObjectData></DTS:Executable>
<DTS:Executable DTS:ExecutableType="Microsoft.SqlServer.Dts.Tasks.ExecuteSQLTask.ExecuteSQLTask, Microsoft.SqlServer.SQLTask, Version=10.0.0.0, Culture=neutral, PublicKeyToken=89845dcd8080cc91" DTS:ThreadHint="0">
<DTS:Property DTS:Name="ExecutionLocation">0</DTS:Property>
<DTS:Property DTS:Name="ExecutionAddress"></DTS:Property>
<DTS:Property DTS:Name="TaskContact">Execute SQL Task; Microsoft Corporation; Microsoft SQL Server 2008 R2; © 2007 Microsoft Corporation; All Rights Reserved;http://www.microsoft.com/sql/support/default.asp;1</DTS:Property>
<DTS:Property DTS:Name="ForceExecValue">0</DTS:Property>
<DTS:Property DTS:Name="ExecValue" DTS:DataType="3">0</DTS:Property>
<DTS:Property DTS:Name="ForceExecutionResult">-1</DTS:Property>
<DTS:Property DTS:Name="Disabled">0</DTS:Property>
<DTS:Property DTS:Name="FailPackageOnFailure">0</DTS:Property>
<DTS:Property DTS:Name="FailParentOnFailure">0</DTS:Property>
<DTS:Property DTS:Name="MaxErrorCount">1</DTS:Property>
<DTS:Property DTS:Name="ISOLevel">1048576</DTS:Property>
<DTS:Property DTS:Name="LocaleID">-1</DTS:Property>
<DTS:Property DTS:Name="TransactionOption">1</DTS:Property>
<DTS:Property DTS:Name="DelayValidation">0</DTS:Property>
<DTS:LoggingOptions>
<DTS:Property DTS:Name="LoggingMode">0</DTS:Property>
<DTS:Property DTS:Name="FilterKind">0</DTS:Property>
<DTS:Property DTS:Name="EventFilter" DTS:DataType="8"></DTS:Property></DTS:LoggingOptions>
<DTS:Property DTS:Name="ObjectName">Formulario 80 INT</DTS:Property>
<DTS:Property DTS:Name="DTSID">{9177902b-3db2-4c9a-8167-7c294405905d}</DTS:Property>
<DTS:Property DTS:Name="Description">Execute SQL Task</DTS:Property>
<DTS:Property DTS:Name="CreationName">Microsoft.SqlServer.Dts.Tasks.ExecuteSQLTask.ExecuteSQLTask, Microsoft.SqlServer.SQLTask, Version=10.0.0.0, Culture=neutral, PublicKeyToken=89845dcd8080cc91</DTS:Property>
<DTS:Property DTS:Name="DisableEventHandlers">0</DTS:Property><DTS:ObjectData><SQLTask:SqlTaskData SQLTask:Connection="{020DAF9F-837C-42F1-9C2F-54AC3945F831}" SQLTask:TimeOut="0" SQLTask:IsStoredProc="False" SQLTask:BypassPrepare="True" SQLTask:SqlStmtSourceType="DirectInput" SQLTask:SqlStatementSource="&#xA;SET DATEFORMAT 'YMD'&#xA;&#xA;	DELETE dbo.AUX_H_R650_FORMULARIO_80_INT&#xA;&#xA;-- Encuentra el Periodo Actual de consumos.&#xA;	DECLARE @Ult_Periodo_Consumo CHAR(6) SET @Ult_Periodo_Consumo = (SELECT MAX(id_periodo) from D_PERIODO where vigente_consumo = 1)&#xA;&#xA;-- Encuentra el Periodo perteneciente a 10 meses anteriores al Periodo Actual. Esto es para no asegurarse de &#xA;	DECLARE @Periodo_Minimo int SET @Periodo_Minimo = (SELECT dbo.Periodo8MesesAtras(@Ult_Periodo_Consumo))&#xA;&#xA;&#xA;		select a11.Id_Tipo_Beneficiario, a16.id_provincia, a11.id_periodo, a11.Id_Padron, a11.id_origen_prestacion, a12.id_cod_resolucion, count(distinct a11.id_persona)  WJXBFS1, 15 as id_entidad_capita, SUBSTRING(CAST(a11.id_periodo as CHAR(6)),1,4) as id_anio&#xA;		into #ZZT397T0OKASP000&#xA;		from H_ORD_AMB_DET a11&#xA;		 join D_PRESTACION a12  on  (a11.id_prestacion = a12.id_prestacion)&#xA;		 join D_TIPOS_BENEFICIARIOS a13  on  (a11.Id_Tipo_Beneficiario = a13.Id_Tipo_Beneficiario)&#xA;		 join D_PRODUCTOS a14  on  (a11.id_producto = a14.id_producto)&#xA;		 join D_PERSONAS a15  on  (a11.id_persona = a15.id_persona)&#xA;		 join D_LOCALIDADES_AFILIADO a16 on  (a15.id_localidad_afiliado = a16.id_localidad_afiliado)&#xA;		where (a11.id_periodo &gt; @Periodo_Minimo AND a11.id_periodo &lt;= @Ult_Periodo_Consumo&#xA;		 and a13.Id_Grupo_Tipo_Beneficiario in (2, 1)&#xA;		 and NOT EXISTS (SELECT * FROM FILTRO_PLAN_PRODUCTO a20 WHERE a11.id_producto=a20.id_producto and a11.id_plan_producto=a20.id_plan_producto)&#xA;		 and a12.id_cod_resolucion in ('O', 'R', 'P', 'N')&#xA;		 and a11.id_origen_prestacion in ('I'))&#xA;		group by a11.Id_Tipo_Beneficiario, a16.id_provincia, a11.id_periodo, a11.Id_Padron, a11.id_origen_prestacion, a12.id_cod_resolucion &#xA;&#xA;		select a11.Id_Tipo_Beneficiario, a16.id_provincia, a11.id_periodo, a11.Id_Padron, a11.id_origen_prestacion, a12.id_cod_resolucion, count(distinct a11.id_persona)  WJXBFS1, 15 as id_entidad_capita, SUBSTRING(CAST(a11.id_periodo as CHAR(6)),1,4) as id_anio&#xA;		into #ZZTKQBI04Y2SP001&#xA;		from H_ORD_INT_DET a11&#xA;		 join D_PRESTACION a12  on  (a11.id_prestacion = a12.id_prestacion)&#xA;		 join D_TIPOS_BENEFICIARIOS a13 on  (a11.Id_Tipo_Beneficiario = a13.Id_Tipo_Beneficiario)&#xA;		 join D_PRODUCTOS a14 on  (a11.id_producto = a14.id_producto)&#xA;		 join D_PERSONAS a15  on  (a11.id_persona = a15.id_persona)&#xA;		 join D_LOCALIDADES_AFILIADO a16 on  (a15.id_localidad_afiliado = a16.id_localidad_afiliado)&#xA;		where (a11.id_periodo &gt; @Periodo_Minimo AND a11.id_periodo &lt;= @Ult_Periodo_Consumo&#xA;		 and a13.Id_Grupo_Tipo_Beneficiario in (2, 1)&#xA;		 and NOT EXISTS (SELECT * FROM FILTRO_PLAN_PRODUCTO a20 WHERE a11.id_producto=a20.id_producto and a11.id_plan_producto=a20.id_plan_producto)&#xA;		 and a12.id_cod_resolucion in ('O', 'R', 'P', 'N')&#xA;		 and a11.id_origen_prestacion in ('I'))&#xA;		group by a11.Id_Tipo_Beneficiario, a16.id_provincia, a11.id_periodo, a11.Id_Padron, a11.id_origen_prestacion, a12.id_cod_resolucion &#xA;&#xA;		INSERT INTO dbo.AUX_H_R650_FORMULARIO_80_INT&#xA;		(ID_Periodo,&#xA;		 id_provincia,&#xA;		 id_padron,&#xA;		 Id_Grupo_Tipo_Beneficiario,&#xA;		 id_cod_resolucion,&#xA;		 cantidad_80I,&#xA;		 id_entidad_capita)&#xA;		select distinct &#xA;		 coalesce(pa11.ID_Periodo, pa12.ID_Periodo)  ID_Periodo,&#xA;		 coalesce(pa11.id_provincia, pa12.id_provincia)  id_provincia,&#xA;		 coalesce(pa11.Id_Padron, pa12.Id_Padron)  Id_Padron,&#xA;		 a13.Id_Grupo_Tipo_Beneficiario  Id_Grupo_Tipo_Beneficiario,&#xA;		 coalesce(pa11.id_cod_resolucion, pa12.id_cod_resolucion)  id_cod_resolucion,&#xA;		 ROUND(ISNULL(((ISNULL(pa11.WJXBFS1, 0) + ISNULL(pa12.WJXBFS1, 0)) / 2.0), 0), 0)  cantidad_80I,&#xA;		pa12.id_entidad_capita&#xA;		from #ZZT397T0OKASP000 pa11&#xA;		 full outer join #ZZTKQBI04Y2SP001 pa12&#xA;		   on  (pa11.ID_Periodo = pa12.ID_Periodo and &#xA;		 pa11.Id_Padron = pa12.Id_Padron and &#xA;		 pa11.Id_Tipo_Beneficiario = pa12.Id_Tipo_Beneficiario and &#xA;		 pa11.id_cod_resolucion = pa12.id_cod_resolucion and &#xA;		 pa11.id_origen_prestacion = pa12.id_origen_prestacion and &#xA;		 pa11.id_provincia = pa12.id_provincia)&#xA;		 join D_TIPOS_BENEFICIARIOS a13  on  (coalesce(pa11.Id_Tipo_Beneficiario, pa12.Id_Tipo_Beneficiario) = a13.Id_Tipo_Beneficiario)&#xA;		 join D_CODIGOS_RESOLUCION650 a14 on  (coalesce(pa11.id_cod_resolucion, pa12.id_cod_resolucion) = a14.id_cod_resolucion)&#xA;		 join D_ORIGEN_PRESTACION a15  on  (coalesce(pa11.id_origen_prestacion, pa12.id_origen_prestacion) = a15.id_origen_prestacion)&#xA;		 join D_PADRON_AFILIADOS a16  on  (coalesce(pa11.Id_Padron, pa12.Id_Padron) = a16.Id_Padron)&#xA;		 join D_PROVINCIA a17  on  (coalesce(pa11.id_provincia, pa12.id_provincia) = a17.id_provincia)&#xA;		 join D_GRUPO_TIPOS_BENEFICIARIO a18  on  (a13.Id_Grupo_Tipo_Beneficiario = a18.Id_Grupo_Tipo_Beneficiario)&#xA;&#xA;		drop table #ZZT397T0OKASP000&#xA;		drop table #ZZTKQBI04Y2SP001&#xA;&#xA;	UPDATE AUX_H_R650_FORMULARIO_80_INT	SET id_anio = P.id_anio, id_trimestre_r650 = P.id_trimestre&#xA;	FROM AUX_H_R650_FORMULARIO_80_INT R JOIN D_PERIODO P on R.id_periodo = P.id_periodo&#xA;	where id_entidad_capita = 15 and R.id_trimestre_r650 is null&#xA;&#xA;	 --Borra periodo ya existente.&#xA;	 DELETE DW_SALUD.dbo.H_R650_FORMULARIO_80_INT&#xA;	 FROM DW_SALUD.dbo.H_R650_FORMULARIO_80_INT A&#xA;	 JOIN dbo.AUX_H_R650_FORMULARIO_80_INT H on H.id_trimestre_r650 = A.id_trimestre_r650 AND H.id_anio = A.id_anio AND H.id_entidad_capita = A.id_entidad_capita AND H.id_periodo = A.id_periodo&#xA;&#xA;	INSERT INTO H_R650_FORMULARIO_80_INT&#xA;	SELECT id_periodo, id_provincia, Id_padron, Id_Grupo_Tipo_Beneficiario, id_cod_resolucion, cantidad_80I, id_trimestre_r650, id_anio, id_entidad_capita&#xA;	FROM dbo.AUX_H_R650_FORMULARIO_80_INT&#xA;		&#xA;	DELETE dbo.AUX_H_R650_FORMULARIO_80_INT&#xA;		" SQLTask:CodePage="1252" SQLTask:ResultType="ResultSetType_None" xmlns:SQLTask="www.microsoft.com/sqlserver/dts/tasks/sqltask"/></DTS:ObjectData></DTS:Executable>
<DTS:PrecedenceConstraint>
<DTS:Property DTS:Name="Value">0</DTS:Property>
<DTS:Property DTS:Name="EvalOp">2</DTS:Property>
<DTS:Property DTS:Name="LogicalAnd">-1</DTS:Property>
<DTS:Property DTS:Name="Expression"></DTS:Property><DTS:Executable IDREF="{4cc10ca0-59b0-421c-91ee-bec8ede70abd}" DTS:IsFrom="-1"/><DTS:Executable IDREF="{3523c1d7-3aad-445b-a10d-3ca975eefe09}" DTS:IsFrom="0"/>
<DTS:Property DTS:Name="ObjectName">Constraint</DTS:Property>
<DTS:Property DTS:Name="DTSID">{D4BA0691-9508-4D1B-8D09-5F53509A3804}</DTS:Property>
<DTS:Property DTS:Name="Description"></DTS:Property>
<DTS:Property DTS:Name="CreationName"></DTS:Property></DTS:PrecedenceConstraint>
<DTS:PrecedenceConstraint>
<DTS:Property DTS:Name="Value">0</DTS:Property>
<DTS:Property DTS:Name="EvalOp">2</DTS:Property>
<DTS:Property DTS:Name="LogicalAnd">-1</DTS:Property>
<DTS:Property DTS:Name="Expression"></DTS:Property><DTS:Executable IDREF="{3523c1d7-3aad-445b-a10d-3ca975eefe09}" DTS:IsFrom="-1"/><DTS:Executable IDREF="{370cbab0-f37c-482d-a8ac-c5f180c0b32e}" DTS:IsFrom="0"/>
<DTS:Property DTS:Name="ObjectName">Constraint 1</DTS:Property>
<DTS:Property DTS:Name="DTSID">{4002DCB3-43A3-465A-AD7D-CF69D7616E97}</DTS:Property>
<DTS:Property DTS:Name="Description"></DTS:Property>
<DTS:Property DTS:Name="CreationName"></DTS:Property></DTS:PrecedenceConstraint>
<DTS:PrecedenceConstraint>
<DTS:Property DTS:Name="Value">0</DTS:Property>
<DTS:Property DTS:Name="EvalOp">2</DTS:Property>
<DTS:Property DTS:Name="LogicalAnd">-1</DTS:Property>
<DTS:Property DTS:Name="Expression"></DTS:Property><DTS:Executable IDREF="{370cbab0-f37c-482d-a8ac-c5f180c0b32e}" DTS:IsFrom="-1"/><DTS:Executable IDREF="{9177902b-3db2-4c9a-8167-7c294405905d}" DTS:IsFrom="0"/>
<DTS:Property DTS:Name="ObjectName">Constraint 2</DTS:Property>
<DTS:Property DTS:Name="DTSID">{BE0858C2-DE94-4AA2-90FC-7ECDF00F2D9F}</DTS:Property>
<DTS:Property DTS:Name="Description"></DTS:Property>
<DTS:Property DTS:Name="CreationName"></DTS:Property></DTS:PrecedenceConstraint>
<DTS:Property DTS:Name="ObjectName">R650_SancorSalud</DTS:Property>
<DTS:Property DTS:Name="DTSID">{8836354A-855F-41EF-A9D4-91CA63B6AC15}</DTS:Property>
<DTS:Property DTS:Name="Description"></DTS:Property>
<DTS:Property DTS:Name="CreationName">SSIS.Package.2</DTS:Property>
<DTS:Property DTS:Name="DisableEventHandlers">0</DTS:Property>
<DTS:PackageVariable>
<DTS:Property DTS:Name="PackageVariableValue" DTS:DataType="8">&lt;PrecedenceConstraint xmlns:xsd="http://www.w3.org/2001/XMLSchema" xmlns:xsi="http://www.w3.org/2001/XMLSchema-instance" xmlns:ddl2="http://schemas.microsoft.com/analysisservices/2003/engine/2" xmlns:ddl2_2="http://schemas.microsoft.com/analysisservices/2003/engine/2/2" xmlns:ddl100_100="http://schemas.microsoft.com/analysisservices/2008/engine/100/100" xmlns:ddl200="http://schemas.microsoft.com/analysisservices/2010/engine/200" xmlns:ddl200_200="http://schemas.microsoft.com/analysisservices/2010/engine/200/200" xmlns:dwd="http://schemas.microsoft.com/DataWarehouse/Designer/1.0"&gt;&lt;dwd:EvalOp&gt;Constraint&lt;/dwd:EvalOp&gt;&lt;/PrecedenceConstraint&gt;</DTS:Property>
<DTS:Property DTS:Name="Namespace">dts-designer-1.0</DTS:Property>
<DTS:Property DTS:Name="ObjectName">{4002DCB3-43A3-465A-AD7D-CF69D7616E97}</DTS:Property>
<DTS:Property DTS:Name="DTSID">{C724D7A0-C60C-42F6-888F-9DBC1B4B0816}</DTS:Property>
<DTS:Property DTS:Name="Description"></DTS:Property>
<DTS:Property DTS:Name="CreationName"></DTS:Property></DTS:PackageVariable>
<DTS:PackageVariable>
<DTS:Property DTS:Name="PackageVariableValue" DTS:DataType="8">&lt;Package xmlns:xsd="http://www.w3.org/2001/XMLSchema" xmlns:xsi="http://www.w3.org/2001/XMLSchema-instance" xmlns:ddl2="http://schemas.microsoft.com/analysisservices/2003/engine/2" xmlns:ddl2_2="http://schemas.microsoft.com/analysisservices/2003/engine/2/2" xmlns:ddl100_100="http://schemas.microsoft.com/analysisservices/2008/engine/100/100" xmlns:ddl200="http://schemas.microsoft.com/analysisservices/2010/engine/200" xmlns:ddl200_200="http://schemas.microsoft.com/analysisservices/2010/engine/200/200" xmlns:dwd="http://schemas.microsoft.com/DataWarehouse/Designer/1.0"&gt;&lt;dwd:DtsControlFlowDiagram&gt;&lt;dwd:BoundingLeft&gt;-19826&lt;/dwd:BoundingLeft&gt;&lt;dwd:BoundingTop&gt;-8615&lt;/dwd:BoundingTop&gt;&lt;dwd:Layout&gt;&lt;dds&gt;
  &lt;diagram fontclsid="{0BE35203-8F91-11CE-9DE3-00AA004BB851}" mouseiconclsid="{0BE35204-8F91-11CE-9DE3-00AA004BB851}" defaultlayout="Microsoft.DataWarehouse.Layout.GraphLayout100" defaultlineroute="Microsoft.DataWarehouse.Layout.GraphLayout100" version="7" nextobject="18" scale="100" pagebreakanchorx="0" pagebreakanchory="0" pagebreaksizex="0" pagebreaksizey="0" scrollleft="-20826" scrolltop="-9615" gridx="150" gridy="150" marginx="1000" marginy="1000" zoom="100" x="21061" y="12779" backcolor="15334399" defaultpersistence="2" PrintPageNumbersMode="3" PrintMarginTop="0" PrintMarginBottom="635" PrintMarginLeft="0" PrintMarginRight="0" marqueeselectionmode="1" mousepointer="0" snaptogrid="0" autotypeannotation="1" showscrollbars="0" viewpagebreaks="0" donotforceconnectorsbehindshapes="1" backpictureclsid="{00000000-0000-0000-0000-000000000000}"&gt;
    &lt;font&gt;
      &lt;ddsxmlobjectstreamwrapper binary="01010000900180380100065461686f6d61" /&gt;
    &lt;/font&gt;
    &lt;mouseicon&gt;
      &lt;ddsxmlobjectstreamwrapper binary="6c74000000000000" /&gt;
    &lt;/mouseicon&gt;
  &lt;/diagram&gt;
  &lt;layoutmanager&gt;
    &lt;ddsxmlobj /&gt;
  &lt;/layoutmanager&gt;
  &lt;ddscontrol controlprogid="DdsShapes.DdsObjectManagedBridge.2" tooltip="Execute SQL Task" left="-19826" top="-8615" logicalid="8" controlid="1" masterid="0" hint1="0" hint2="0" width="3889" height="1164" noresize="0" nomove="0" nodefaultattachpoints="0" autodrag="1" usedefaultiddshape="1" selectable="1" showselectionhandles="1" allownudging="1" isannotation="0" dontautolayout="0" groupcollapsed="0" tabstop="1" visible="1" snaptogrid="0"&gt;
    &lt;control&gt;
      &lt;ddsxmlobjectstreaminitwrapper binary="00080000310f00008c040000" /&gt;
    &lt;/control&gt;
    &lt;layoutobject&gt;
      &lt;ddsxmlobj&gt;
        &lt;property name="LogicalObject" value="{4cc10ca0-59b0-421c-91ee-bec8ede70abd}" vartype="8" /&gt;
        &lt;property name="ShowConnectorSource" value="0" vartype="2" /&gt;
      &lt;/ddsxmlobj&gt;
    &lt;/layoutobject&gt;
    &lt;shape groupshapeid="0" groupnode="0" /&gt;
  &lt;/ddscontrol&gt;
  &lt;ddscontrol controlprogid="DdsShapes.DdsObjectManagedBridge.2" tooltip="Execute SQL Task" left="-19507" top="-6632" logicalid="9" controlid="2" masterid="0" hint1="0" hint2="0" width="3254" height="1164" noresize="0" nomove="0" nodefaultattachpoints="0" autodrag="1" usedefaultiddshape="1" selectable="1" showselectionhandles="1" allownudging="1" isannotation="0" dontautolayout="0" groupcollapsed="0" tabstop="1" visible="1" snaptogrid="0"&gt;
    &lt;control&gt;
      &lt;ddsxmlobjectstreaminitwrapper binary="00080000b60c00008c040000" /&gt;
    &lt;/control&gt;
    &lt;layoutobject&gt;
      &lt;ddsxmlobj&gt;
        &lt;property name="LogicalObject" value="{3523c1d7-3aad-445b-a10d-3ca975eefe09}" vartype="8" /&gt;
        &lt;property name="ShowConnectorSource" value="0" vartype="2" /&gt;
      &lt;/ddsxmlobj&gt;
    &lt;/layoutobject&gt;
    &lt;shape groupshapeid="0" groupnode="0" /&gt;
  &lt;/ddscontrol&gt;
  &lt;ddscontrol controlprogid="MSDDS.Polyline" left="-18281" top="-7850" logicalid="10" controlid="3" masterid="0" hint1="0" hint2="0" width="801" height="1718" noresize="0" nomove="0" nodefaultattachpoints="1" autodrag="0" usedefaultiddshape="0" selectable="1" showselectionhandles="0" allownudging="1" isannotation="0" dontautolayout="0" groupcollapsed="0" tabstop="1" visible="1" snaptogrid="0"&gt;
    &lt;control&gt;
      &lt;ddsxmlobj&gt;
        &lt;polyline endtypedst="3" endtypesrc="1" usercolor="32768" linestyle="0" linerender="2" customendtypedstid="0" customendtypesrcid="0" adornsvisible="1" /&gt;
      &lt;/ddsxmlobj&gt;
    &lt;/control&gt;
    &lt;layoutobject&gt;
      &lt;ddsxmlobj&gt;
        &lt;property name="LogicalObject" value="{D4BA0691-9508-4D1B-8D09-5F53509A3804}" vartype="8" /&gt;
        &lt;property name="Virtual" value="0" vartype="11" /&gt;
        &lt;property name="VisibleAP" value="0" vartype="3" /&gt;
      &lt;/ddsxmlobj&gt;
    &lt;/layoutobject&gt;
    &lt;connector lineroutestyle="Microsoft.DataWarehouse.Layout.GraphLayout100" sourceid="1" destid="2" sourceattachpoint="7" destattachpoint="4" segmenteditmode="0" bendpointeditmode="0" bendpointvisibility="2" relatedid="0" virtual="0"&gt;
      &lt;point x="-17882" y="-7451" /&gt;
      &lt;point x="-17882" y="-7041" /&gt;
      &lt;point x="-17880" y="-7041" /&gt;
      &lt;point x="-17880" y="-6632" /&gt;
    &lt;/connector&gt;
  &lt;/ddscontrol&gt;
  &lt;ddscontrol controlprogid="DdsShapes.DdsObjectManagedBridge.2" tooltip="Execute SQL Task" left="-19826" top="-4626" logicalid="11" controlid="4" masterid="0" hint1="0" hint2="0" width="3889" height="1164" noresize="0" nomove="0" nodefaultattachpoints="0" autodrag="1" usedefaultiddshape="1" selectable="1" showselectionhandles="1" allownudging="1" isannotation="0" dontautolayout="0" groupcollapsed="0" tabstop="1" visible="1" snaptogrid="0"&gt;
    &lt;control&gt;
      &lt;ddsxmlobjectstreaminitwrapper binary="00080000310f00008c040000" /&gt;
    &lt;/control&gt;
    &lt;layoutobject&gt;
      &lt;ddsxmlobj&gt;
        &lt;property name="LogicalObject" value="{370cbab0-f37c-482d-a8ac-c5f180c0b32e}" vartype="8" /&gt;
        &lt;property name="ShowConnectorSource" value="0" vartype="2" /&gt;
      &lt;/ddsxmlobj&gt;
    &lt;/layoutobject&gt;
    &lt;shape groupshapeid="0" groupnode="0" /&gt;
  &lt;/ddscontrol&gt;
  &lt;ddscontrol controlprogid="MSDDS.Polyline" left="-18281" top="-5867" logicalid="12" controlid="5" masterid="0" hint1="0" hint2="0" width="801" height="1741" noresize="0" nomove="0" nodefaultattachpoints="1" autodrag="0" usedefaultiddshape="0" selectable="1" showselectionhandles="0" allownudging="1" isannotation="0" dontautolayout="0" groupcollapsed="0" tabstop="1" visible="1" snaptogrid="0"&gt;
    &lt;control&gt;
      &lt;ddsxmlobj&gt;
        &lt;polyline endtypedst="3" endtypesrc="1" usercolor="32768" linestyle="0" linerender="2" customendtypedstid="0" customendtypesrcid="0" adornsvisible="1" /&gt;
      &lt;/ddsxmlobj&gt;
    &lt;/control&gt;
    &lt;layoutobject&gt;
      &lt;ddsxmlobj&gt;
        &lt;property name="LogicalObject" value="{4002DCB3-43A3-465A-AD7D-CF69D7616E97}" vartype="8" /&gt;
        &lt;property name="Virtual" value="0" vartype="11" /&gt;
        &lt;property name="VisibleAP" value="0" vartype="3" /&gt;
      &lt;/ddsxmlobj&gt;
    &lt;/layoutobject&gt;
    &lt;connector lineroutestyle="Microsoft.DataWarehouse.Layout.GraphLayout100" sourceid="2" destid="4" sourceattachpoint="5" destattachpoint="6" segmenteditmode="0" bendpointeditmode="0" bendpointvisibility="2" relatedid="0" virtual="0"&gt;
      &lt;point x="-17880" y="-5468" /&gt;
      &lt;point x="-17880" y="-5047" /&gt;
      &lt;point x="-17882" y="-5047" /&gt;
      &lt;point x="-17882" y="-4626" /&gt;
    &lt;/connector&gt;
  &lt;/ddscontrol&gt;
  &lt;ddscontrol controlprogid="DdsShapes.DdsObjectManagedBridge.2" tooltip="Execute SQL Task" left="-19774" top="-2803" logicalid="13" controlid="6" masterid="0" hint1="0" hint2="0" width="3784" height="1164" noresize="0" nomove="0" nodefaultattachpoints="0" autodrag="1" usedefaultiddshape="1" selectable="1" showselectionhandles="1" allownudging="1" isannotation="0" dontautolayout="0" groupcollapsed="0" tabstop="1" visible="1" snaptogrid="0"&gt;
    &lt;control&gt;
      &lt;ddsxmlobjectstreaminitwrapper binary="00080000c80e00008c040000" /&gt;
    &lt;/control&gt;
    &lt;layoutobject&gt;
      &lt;ddsxmlobj&gt;
        &lt;property name="LogicalObject" value="{9177902b-3db2-4c9a-8167-7c294405905d}" vartype="8" /&gt;
        &lt;property name="ShowConnectorSource" value="0" vartype="2" /&gt;
      &lt;/ddsxmlobj&gt;
    &lt;/layoutobject&gt;
    &lt;shape groupshapeid="0" groupnode="0" /&gt;
  &lt;/ddscontrol&gt;
  &lt;ddscontrol controlprogid="MSDDS.Polyline" left="-18281" top="-3861" logicalid="14" controlid="7" masterid="0" hint1="0" hint2="0" width="799" height="1558" noresize="0" nomove="0" nodefaultattachpoints="1" autodrag="0" usedefaultiddshape="0" selectable="1" showselectionhandles="0" allownudging="1" isannotation="0" dontautolayout="0" groupcollapsed="0" tabstop="1" visible="1" snaptogrid="0"&gt;
    &lt;control&gt;
      &lt;ddsxmlobj&gt;
        &lt;polyline endtypedst="3" endtypesrc="1" usercolor="32768" linestyle="0" linerender="2" customendtypedstid="0" customendtypesrcid="0" adornsvisible="1" /&gt;
      &lt;/ddsxmlobj&gt;
    &lt;/control&gt;
    &lt;layoutobject&gt;
      &lt;ddsxmlobj&gt;
        &lt;property name="LogicalObject" value="{BE0858C2-DE94-4AA2-90FC-7ECDF00F2D9F}" vartype="8" /&gt;
        &lt;property name="Virtual" value="0" vartype="11" /&gt;
        &lt;property name="VisibleAP" value="0" vartype="3" /&gt;
      &lt;/ddsxmlobj&gt;
    &lt;/layoutobject&gt;
    &lt;connector lineroutestyle="Microsoft.DataWarehouse.Layout.GraphLayout100" sourceid="4" destid="6" sourceattachpoint="7" destattachpoint="6" segmenteditmode="0" bendpointeditmode="0" bendpointvisibility="2" relatedid="0" virtual="0"&gt;
      &lt;point x="-17882" y="-3462" /&gt;
      &lt;point x="-17882" y="-2803" /&gt;
    &lt;/connector&gt;
  &lt;/ddscontrol&gt;
&lt;/dds&gt;&lt;/dwd:Layout&gt;&lt;dwd:PersistedViewPortLeft&gt;-20826&lt;/dwd:PersistedViewPortLeft&gt;&lt;dwd:PersistedViewPortTop&gt;-9615&lt;/dwd:PersistedViewPortTop&gt;&lt;/dwd:DtsControlFlowDiagram&gt;&lt;/Package&gt;</DTS:Property>
<DTS:Property DTS:Name="Namespace">dts-designer-1.0</DTS:Property>
<DTS:Property DTS:Name="ObjectName">{814B49BA-EE77-4085-946B-0E06804D56FB}</DTS:Property>
<DTS:Property DTS:Name="DTSID">{A1A9AEAF-0229-4FC7-9F5F-62A79CF50B42}</DTS:Property>
<DTS:Property DTS:Name="Description"></DTS:Property>
<DTS:Property DTS:Name="CreationName"></DTS:Property></DTS:PackageVariable>
<DTS:PackageVariable>
<DTS:Property DTS:Name="PackageVariableValue" DTS:DataType="8">&lt;PrecedenceConstraint xmlns:xsd="http://www.w3.org/2001/XMLSchema" xmlns:xsi="http://www.w3.org/2001/XMLSchema-instance" xmlns:ddl2="http://schemas.microsoft.com/analysisservices/2003/engine/2" xmlns:ddl2_2="http://schemas.microsoft.com/analysisservices/2003/engine/2/2" xmlns:ddl100_100="http://schemas.microsoft.com/analysisservices/2008/engine/100/100" xmlns:ddl200="http://schemas.microsoft.com/analysisservices/2010/engine/200" xmlns:ddl200_200="http://schemas.microsoft.com/analysisservices/2010/engine/200/200" xmlns:dwd="http://schemas.microsoft.com/DataWarehouse/Designer/1.0"&gt;&lt;dwd:EvalOp&gt;Constraint&lt;/dwd:EvalOp&gt;&lt;/PrecedenceConstraint&gt;</DTS:Property>
<DTS:Property DTS:Name="Namespace">dts-designer-1.0</DTS:Property>
<DTS:Property DTS:Name="ObjectName">{BE0858C2-DE94-4AA2-90FC-7ECDF00F2D9F}</DTS:Property>
<DTS:Property DTS:Name="DTSID">{AE681B50-C361-4769-8E71-13263D951FC3}</DTS:Property>
<DTS:Property DTS:Name="Description"></DTS:Property>
<DTS:Property DTS:Name="CreationName"></DTS:Property></DTS:PackageVariable>
<DTS:PackageVariable>
<DTS:Property DTS:Name="PackageVariableValue" DTS:DataType="8">&lt;PrecedenceConstraint xmlns:xsd="http://www.w3.org/2001/XMLSchema" xmlns:xsi="http://www.w3.org/2001/XMLSchema-instance" xmlns:ddl2="http://schemas.microsoft.com/analysisservices/2003/engine/2" xmlns:ddl2_2="http://schemas.microsoft.com/analysisservices/2003/engine/2/2" xmlns:ddl100_100="http://schemas.microsoft.com/analysisservices/2008/engine/100/100" xmlns:ddl200="http://schemas.microsoft.com/analysisservices/2010/engine/200" xmlns:ddl200_200="http://schemas.microsoft.com/analysisservices/2010/engine/200/200" xmlns:dwd="http://schemas.microsoft.com/DataWarehouse/Designer/1.0"&gt;&lt;dwd:EvalOp&gt;Constraint&lt;/dwd:EvalOp&gt;&lt;/PrecedenceConstraint&gt;</DTS:Property>
<DTS:Property DTS:Name="Namespace">dts-designer-1.0</DTS:Property>
<DTS:Property DTS:Name="ObjectName">{D4BA0691-9508-4D1B-8D09-5F53509A3804}</DTS:Property>
<DTS:Property DTS:Name="DTSID">{5D290990-1493-4463-B5AD-D0B562B98487}</DTS:Property>
<DTS:Property DTS:Name="Description"></DTS:Property>
<DTS:Property DTS:Name="CreationName"></DTS:Property></DTS:PackageVariable>
<DTS:PackageVariable>
<DTS:Property DTS:Name="PackageVariableValue" DTS:DataType="8">&lt;Package xmlns:xsd="http://www.w3.org/2001/XMLSchema" xmlns:xsi="http://www.w3.org/2001/XMLSchema-instance" xmlns:ddl2="http://schemas.microsoft.com/analysisservices/2003/engine/2" xmlns:ddl2_2="http://schemas.microsoft.com/analysisservices/2003/engine/2/2" xmlns:ddl100_100="http://schemas.microsoft.com/analysisservices/2008/engine/100/100" xmlns:ddl200="http://schemas.microsoft.com/analysisservices/2010/engine/200" xmlns:ddl200_200="http://schemas.microsoft.com/analysisservices/2010/engine/200/200" xmlns:dwd="http://schemas.microsoft.com/DataWarehouse/Designer/1.0"&gt;&lt;dwd:DtsControlFlowDiagram&gt;&lt;dwd:BoundingLeft&gt;-19826&lt;/dwd:BoundingLeft&gt;&lt;dwd:BoundingTop&gt;-8615&lt;/dwd:BoundingTop&gt;&lt;dwd:Layout&gt;&lt;dds&gt;
  &lt;diagram fontclsid="{0BE35203-8F91-11CE-9DE3-00AA004BB851}" mouseiconclsid="{0BE35204-8F91-11CE-9DE3-00AA004BB851}" defaultlayout="Microsoft.DataWarehouse.Layout.GraphLayout100" defaultlineroute="Microsoft.DataWarehouse.Layout.GraphLayout100" version="7" nextobject="18" scale="100" pagebreakanchorx="0" pagebreakanchory="0" pagebreaksizex="0" pagebreaksizey="0" scrollleft="-20826" scrolltop="-9615" gridx="150" gridy="150" marginx="1000" marginy="1000" zoom="100" x="21061" y="12779" backcolor="15334399" defaultpersistence="2" PrintPageNumbersMode="3" PrintMarginTop="0" PrintMarginBottom="635" PrintMarginLeft="0" PrintMarginRight="0" marqueeselectionmode="1" mousepointer="0" snaptogrid="0" autotypeannotation="1" showscrollbars="0" viewpagebreaks="0" donotforceconnectorsbehindshapes="1" backpictureclsid="{00000000-0000-0000-0000-000000000000}"&gt;
    &lt;font&gt;
      &lt;ddsxmlobjectstreamwrapper binary="01010000900180380100065461686f6d61" /&gt;
    &lt;/font&gt;
    &lt;mouseicon&gt;
      &lt;ddsxmlobjectstreamwrapper binary="6c74000000000000" /&gt;
    &lt;/mouseicon&gt;
  &lt;/diagram&gt;
  &lt;layoutmanager&gt;
    &lt;ddsxmlobj /&gt;
  &lt;/layoutmanager&gt;
  &lt;ddscontrol controlprogid="DdsShapes.DdsObjectManagedBridge.2" tooltip="Execute SQL Task" left="-19826" top="-8615" logicalid="8" controlid="1" masterid="0" hint1="0" hint2="0" width="3889" height="1164" noresize="0" nomove="0" nodefaultattachpoints="0" autodrag="1" usedefaultiddshape="1" selectable="1" showselectionhandles="1" allownudging="1" isannotation="0" dontautolayout="0" groupcollapsed="0" tabstop="1" visible="1" snaptogrid="0"&gt;
    &lt;control&gt;
      &lt;ddsxmlobjectstreaminitwrapper binary="00080000310f00008c040000" /&gt;
    &lt;/control&gt;
    &lt;layoutobject&gt;
      &lt;ddsxmlobj&gt;
        &lt;property name="LogicalObject" value="{4cc10ca0-59b0-421c-91ee-bec8ede70abd}" vartype="8" /&gt;
        &lt;property name="ShowConnectorSource" value="0" vartype="2" /&gt;
      &lt;/ddsxmlobj&gt;
    &lt;/layoutobject&gt;
    &lt;shape groupshapeid="0" groupnode="0" /&gt;
  &lt;/ddscontrol&gt;
  &lt;ddscontrol controlprogid="DdsShapes.DdsObjectManagedBridge.2" tooltip="Execute SQL Task" left="-19507" top="-6632" logicalid="9" controlid="2" masterid="0" hint1="0" hint2="0" width="3254" height="1164" noresize="0" nomove="0" nodefaultattachpoints="0" autodrag="1" usedefaultiddshape="1" selectable="1" showselectionhandles="1" allownudging="1" isannotation="0" dontautolayout="0" groupcollapsed="0" tabstop="1" visible="1" snaptogrid="0"&gt;
    &lt;control&gt;
      &lt;ddsxmlobjectstreaminitwrapper binary="00080000b60c00008c040000" /&gt;
    &lt;/control&gt;
    &lt;layoutobject&gt;
      &lt;ddsxmlobj&gt;
        &lt;property name="LogicalObject" value="{3523c1d7-3aad-445b-a10d-3ca975eefe09}" vartype="8" /&gt;
        &lt;property name="ShowConnectorSource" value="0" vartype="2" /&gt;
      &lt;/ddsxmlobj&gt;
    &lt;/layoutobject&gt;
    &lt;shape groupshapeid="0" groupnode="0" /&gt;
  &lt;/ddscontrol&gt;
  &lt;ddscontrol controlprogid="MSDDS.Polyline" left="-18281" top="-7850" logicalid="10" controlid="3" masterid="0" hint1="0" hint2="0" width="801" height="1718" noresize="0" nomove="0" nodefaultattachpoints="1" autodrag="0" usedefaultiddshape="0" selectable="1" showselectionhandles="0" allownudging="1" isannotation="0" dontautolayout="0" groupcollapsed="0" tabstop="1" visible="1" snaptogrid="0"&gt;
    &lt;control&gt;
      &lt;ddsxmlobj&gt;
        &lt;polyline endtypedst="3" endtypesrc="1" usercolor="32768" linestyle="0" linerender="2" customendtypedstid="0" customendtypesrcid="0" adornsvisible="1" /&gt;
      &lt;/ddsxmlobj&gt;
    &lt;/control&gt;
    &lt;layoutobject&gt;
      &lt;ddsxmlobj&gt;
        &lt;property name="LogicalObject" value="{D4BA0691-9508-4D1B-8D09-5F53509A3804}" vartype="8" /&gt;
        &lt;property name="Virtual" value="0" vartype="11" /&gt;
        &lt;property name="VisibleAP" value="0" vartype="3" /&gt;
      &lt;/ddsxmlobj&gt;
    &lt;/layoutobject&gt;
    &lt;connector lineroutestyle="Microsoft.DataWarehouse.Layout.GraphLayout100" sourceid="1" destid="2" sourceattachpoint="7" destattachpoint="4" segmenteditmode="0" bendpointeditmode="0" bendpointvisibility="2" relatedid="0" virtual="0"&gt;
      &lt;point x="-17882" y="-7451" /&gt;
      &lt;point x="-17882" y="-7041" /&gt;
      &lt;point x="-17880" y="-7041" /&gt;
      &lt;point x="-17880" y="-6632" /&gt;
    &lt;/connector&gt;
  &lt;/ddscontrol&gt;
  &lt;ddscontrol controlprogid="DdsShapes.DdsObjectManagedBridge.2" tooltip="Execute SQL Task" left="-19826" top="-4626" logicalid="11" controlid="4" masterid="0" hint1="0" hint2="0" width="3889" height="1164" noresize="0" nomove="0" nodefaultattachpoints="0" autodrag="1" usedefaultiddshape="1" selectable="1" showselectionhandles="1" allownudging="1" isannotation="0" dontautolayout="0" groupcollapsed="0" tabstop="1" visible="1" snaptogrid="0"&gt;
    &lt;control&gt;
      &lt;ddsxmlobjectstreaminitwrapper binary="00080000310f00008c040000" /&gt;
    &lt;/control&gt;
    &lt;layoutobject&gt;
      &lt;ddsxmlobj&gt;
        &lt;property name="LogicalObject" value="{370cbab0-f37c-482d-a8ac-c5f180c0b32e}" vartype="8" /&gt;
        &lt;property name="ShowConnectorSource" value="0" vartype="2" /&gt;
      &lt;/ddsxmlobj&gt;
    &lt;/layoutobject&gt;
    &lt;shape groupshapeid="0" groupnode="0" /&gt;
  &lt;/ddscontrol&gt;
  &lt;ddscontrol controlprogid="MSDDS.Polyline" left="-18281" top="-5867" logicalid="12" controlid="5" masterid="0" hint1="0" hint2="0" width="801" height="1741" noresize="0" nomove="0" nodefaultattachpoints="1" autodrag="0" usedefaultiddshape="0" selectable="1" showselectionhandles="0" allownudging="1" isannotation="0" dontautolayout="0" groupcollapsed="0" tabstop="1" visible="1" snaptogrid="0"&gt;
    &lt;control&gt;
      &lt;ddsxmlobj&gt;
        &lt;polyline endtypedst="3" endtypesrc="1" usercolor="32768" linestyle="0" linerender="2" customendtypedstid="0" customendtypesrcid="0" adornsvisible="1" /&gt;
      &lt;/ddsxmlobj&gt;
    &lt;/control&gt;
    &lt;layoutobject&gt;
      &lt;ddsxmlobj&gt;
        &lt;property name="LogicalObject" value="{4002DCB3-43A3-465A-AD7D-CF69D7616E97}" vartype="8" /&gt;
        &lt;property name="Virtual" value="0" vartype="11" /&gt;
        &lt;property name="VisibleAP" value="0" vartype="3" /&gt;
      &lt;/ddsxmlobj&gt;
    &lt;/layoutobject&gt;
    &lt;connector lineroutestyle="Microsoft.DataWarehouse.Layout.GraphLayout100" sourceid="2" destid="4" sourceattachpoint="5" destattachpoint="6" segmenteditmode="0" bendpointeditmode="0" bendpointvisibility="2" relatedid="0" virtual="0"&gt;
      &lt;point x="-17880" y="-5468" /&gt;
      &lt;point x="-17880" y="-5047" /&gt;
      &lt;point x="-17882" y="-5047" /&gt;
      &lt;point x="-17882" y="-4626" /&gt;
    &lt;/connector&gt;
  &lt;/ddscontrol&gt;
  &lt;ddscontrol controlprogid="DdsShapes.DdsObjectManagedBridge.2" tooltip="Execute SQL Task" left="-19774" top="-2803" logicalid="13" controlid="6" masterid="0" hint1="0" hint2="0" width="3784" height="1164" noresize="0" nomove="0" nodefaultattachpoints="0" autodrag="1" usedefaultiddshape="1" selectable="1" showselectionhandles="1" allownudging="1" isannotation="0" dontautolayout="0" groupcollapsed="0" tabstop="1" visible="1" snaptogrid="0"&gt;
    &lt;control&gt;
      &lt;ddsxmlobjectstreaminitwrapper binary="00080000c80e00008c040000" /&gt;
    &lt;/control&gt;
    &lt;layoutobject&gt;
      &lt;ddsxmlobj&gt;
        &lt;property name="LogicalObject" value="{9177902b-3db2-4c9a-8167-7c294405905d}" vartype="8" /&gt;
        &lt;property name="ShowConnectorSource" value="0" vartype="2" /&gt;
      &lt;/ddsxmlobj&gt;
    &lt;/layoutobject&gt;
    &lt;shape groupshapeid="0" groupnode="0" /&gt;
  &lt;/ddscontrol&gt;
  &lt;ddscontrol controlprogid="MSDDS.Polyline" left="-18281" top="-3861" logicalid="14" controlid="7" masterid="0" hint1="0" hint2="0" width="799" height="1558" noresize="0" nomove="0" nodefaultattachpoints="1" autodrag="0" usedefaultiddshape="0" selectable="1" showselectionhandles="0" allownudging="1" isannotation="0" dontautolayout="0" groupcollapsed="0" tabstop="1" visible="1" snaptogrid="0"&gt;
    &lt;control&gt;
      &lt;ddsxmlobj&gt;
        &lt;polyline endtypedst="3" endtypesrc="1" usercolor="32768" linestyle="0" linerender="2" customendtypedstid="0" customendtypesrcid="0" adornsvisible="1" /&gt;
      &lt;/ddsxmlobj&gt;
    &lt;/control&gt;
    &lt;layoutobject&gt;
      &lt;ddsxmlobj&gt;
        &lt;property name="LogicalObject" value="{BE0858C2-DE94-4AA2-90FC-7ECDF00F2D9F}" vartype="8" /&gt;
        &lt;property name="Virtual" value="0" vartype="11" /&gt;
        &lt;property name="VisibleAP" value="0" vartype="3" /&gt;
      &lt;/ddsxmlobj&gt;
    &lt;/layoutobject&gt;
    &lt;connector lineroutestyle="Microsoft.DataWarehouse.Layout.GraphLayout100" sourceid="4" destid="6" sourceattachpoint="7" destattachpoint="6" segmenteditmode="0" bendpointeditmode="0" bendpointvisibility="2" relatedid="0" virtual="0"&gt;
      &lt;point x="-17882" y="-3462" /&gt;
      &lt;point x="-17882" y="-2803" /&gt;
    &lt;/connector&gt;
  &lt;/ddscontrol&gt;
&lt;/dds&gt;&lt;/dwd:Layout&gt;&lt;dwd:PersistedViewPortLeft&gt;-20826&lt;/dwd:PersistedViewPortLeft&gt;&lt;dwd:PersistedViewPortTop&gt;-9615&lt;/dwd:PersistedViewPortTop&gt;&lt;/dwd:DtsControlFlowDiagram&gt;&lt;/Package&gt;</DTS:Property>
<DTS:Property DTS:Name="Namespace">dts-designer-1.0</DTS:Property>
<DTS:Property DTS:Name="ObjectName">package-diagram</DTS:Property>
<DTS:Property DTS:Name="DTSID">{6EB6FE6D-7E89-4229-81B6-D81937675703}</DTS:Property>
<DTS:Property DTS:Name="Description"></DTS:Property>
<DTS:Property DTS:Name="CreationName"></DTS:Property></DTS:PackageVariable></DTS:Executable>